
{
  "fio version" : "fio-3.37",
  "timestamp" : 1733246657,
  "time" : "Tue Dec  3 18:24:17 2024",
  "global options" : {
    "directory" : "/mnt/benchmark/replica2/",
    "ioengine" : "libaio",
    "direct" : "1",
    "buffered" : "0",
    "invalidate" : "1",
    "time_based" : "1",
    "runtime" : "50",
    "size" : "16G",
    "group_reporting" : "1",
    "loops" : "1",
    "directory" : "/mnt/benchmark/replica2/",
    "ioengine" : "libaio",
    "direct" : "1",
    "buffered" : "0",
    "invalidate" : "1",
    "time_based" : "1",
    "runtime" : "50",
    "size" : "16G",
    "group_reporting" : "1",
    "loops" : "1",
    "directory" : "/mnt/benchmark/replica2/",
    "ioengine" : "libaio",
    "direct" : "1",
    "buffered" : "0",
    "invalidate" : "1",
    "time_based" : "1",
    "runtime" : "50",
    "size" : "16G",
    "group_reporting" : "1",
    "loops" : "1"
  },
  "client_stats" : [
    {
      "jobname" : "Write",
      "groupid" : 0,
      "job_start" : 1733246658439,
      "error" : 0,
      "job options" : {
        "rw" : "write",
        "bs" : "8m",
        "numjobs" : "128"
      },
      "read" : {
        "io_bytes" : 0,
        "io_kbytes" : 0,
        "bw_bytes" : 0,
        "bw" : 0,
        "iops" : 0.000000,
        "runtime" : 0,
        "total_ios" : 0,
        "short_ios" : 0,
        "drop_ios" : 0,
        "slat_ns" : {
          "min" : 0,
          "max" : 0,
          "mean" : 0.000000,
          "stddev" : 0.000000,
          "N" : 0
        },
        "clat_ns" : {
          "min" : 0,
          "max" : 0,
          "mean" : 0.000000,
          "stddev" : 0.000000,
          "N" : 0
        },
        "lat_ns" : {
          "min" : 0,
          "max" : 0,
          "mean" : 0.000000,
          "stddev" : 0.000000,
          "N" : 0
        },
        "bw_min" : 0,
        "bw_max" : 0,
        "bw_agg" : 0.000000,
        "bw_mean" : 0.000000,
        "bw_dev" : 0.000000,
        "bw_samples" : 0,
        "iops_min" : 0,
        "iops_max" : 0,
        "iops_mean" : 0.000000,
        "iops_stddev" : 0.000000,
        "iops_samples" : 0
      },
      "write" : {
        "io_bytes" : 69902270464,
        "io_kbytes" : 68263936,
        "bw_bytes" : 1352284114,
        "bw" : 1320589,
        "iops" : 161.204829,
        "runtime" : 51692,
        "total_ios" : 8333,
        "short_ios" : 0,
        "drop_ios" : 0,
        "slat_ns" : {
          "min" : 354985,
          "max" : 79752046,
          "mean" : 2598278.335293,
          "stddev" : 7810325.507231,
          "N" : 8333
        },
        "clat_ns" : {
          "min" : 27919358,
          "max" : 8160309899,
          "mean" : 773816539.790712,
          "stddev" : 851212939.328620,
          "N" : 8333,
          "percentile" : {
            "1.000000" : 79167488,
            "5.000000" : 139460608,
            "10.000000" : 187695104,
            "20.000000" : 265289728,
            "30.000000" : 329252864,
            "40.000000" : 396361728,
            "50.000000" : 467664896,
            "60.000000" : 574619648,
            "70.000000" : 750780416,
            "80.000000" : 1082130432,
            "90.000000" : 1753219072,
            "95.000000" : 2466250752,
            "99.000000" : 4462739456,
            "99.500000" : 5066719232,
            "99.900000" : 6811549696,
            "99.950000" : 7147094016,
            "99.990000" : 8153726976
          }
        },
        "lat_ns" : {
          "min" : 37504949,
          "max" : 8160842536,
          "mean" : 776414818.126005,
          "stddev" : 851299175.587143,
          "N" : 8333
        },
        "bw_min" : 2085042,
        "bw_max" : 5783877,
        "bw_agg" : 100.000000,
        "bw_mean" : 2657885.721132,
        "bw_dev" : 8105.692283,
        "bw_samples" : 6476,
        "iops_min" : 162,
        "iops_max" : 705,
        "iops_mean" : 320.335559,
        "iops_stddev" : 1.007119,
        "iops_samples" : 6476
      },
      "trim" : {
        "io_bytes" : 0,
        "io_kbytes" : 0,
        "bw_bytes" : 0,
        "bw" : 0,
        "iops" : 0.000000,
        "runtime" : 0,
        "total_ios" : 0,
        "short_ios" : 0,
        "drop_ios" : 0,
        "slat_ns" : {
          "min" : 0,
          "max" : 0,
          "mean" : 0.000000,
          "stddev" : 0.000000,
          "N" : 0
        },
        "clat_ns" : {
          "min" : 0,
          "max" : 0,
          "mean" : 0.000000,
          "stddev" : 0.000000,
          "N" : 0
        },
        "lat_ns" : {
          "min" : 0,
          "max" : 0,
          "mean" : 0.000000,
          "stddev" : 0.000000,
          "N" : 0
        },
        "bw_min" : 0,
        "bw_max" : 0,
        "bw_agg" : 0.000000,
        "bw_mean" : 0.000000,
        "bw_dev" : 0.000000,
        "bw_samples" : 0,
        "iops_min" : 0,
        "iops_max" : 0,
        "iops_mean" : 0.000000,
        "iops_stddev" : 0.000000,
        "iops_samples" : 0
      },
      "sync" : {
        "total_ios" : 0,
        "lat_ns" : {
          "min" : 0,
          "max" : 0,
          "mean" : 0.000000,
          "stddev" : 0.000000,
          "N" : 0
        }
      },
      "job_runtime" : 6469916,
      "usr_cpu" : 0.033045,
      "sys_cpu" : 0.114669,
      "ctx" : 10380,
      "majf" : 28,
      "minf" : 3404,
      "iodepth_level" : {
        "1" : 100.000000,
        "2" : 0.000000,
        "4" : 0.000000,
        "8" : 0.000000,
        "16" : 0.000000,
        "32" : 0.000000,
        ">=64" : 0.000000
      },
      "iodepth_submit" : {
        "0" : 0.000000,
        "4" : 100.000000,
        "8" : 0.000000,
        "16" : 0.000000,
        "32" : 0.000000,
        "64" : 0.000000,
        ">=64" : 0.000000
      },
      "iodepth_complete" : {
        "0" : 0.000000,
        "4" : 100.000000,
        "8" : 0.000000,
        "16" : 0.000000,
        "32" : 0.000000,
        "64" : 0.000000,
        ">=64" : 0.000000
      },
      "latency_ns" : {
        "2" : 0.000000,
        "4" : 0.000000,
        "10" : 0.000000,
        "20" : 0.000000,
        "50" : 0.000000,
        "100" : 0.000000,
        "250" : 0.000000,
        "500" : 0.000000,
        "750" : 0.000000,
        "1000" : 0.000000
      },
      "latency_us" : {
        "2" : 0.000000,
        "4" : 0.000000,
        "10" : 0.000000,
        "20" : 0.000000,
        "50" : 0.000000,
        "100" : 0.000000,
        "250" : 0.000000,
        "500" : 0.000000,
        "750" : 0.000000,
        "1000" : 0.000000
      },
      "latency_ms" : {
        "2" : 0.000000,
        "4" : 0.000000,
        "10" : 0.000000,
        "20" : 0.000000,
        "50" : 0.144006,
        "100" : 1.884075,
        "250" : 15.972639,
        "500" : 35.581423,
        "750" : 16.428657,
        "1000" : 7.848314,
        "2000" : 14.400576,
        ">=2000" : 7.740310
      },
      "latency_depth" : 1,
      "latency_target" : 0,
      "latency_percentile" : 100.000000,
      "latency_window" : 0,
      "hostname" : "10.128.2.177",
      "port" : 8765
    },
    {
      "jobname" : "Write",
      "groupid" : 0,
      "job_start" : 1733246658442,
      "error" : 0,
      "job options" : {
        "rw" : "write",
        "bs" : "8m",
        "numjobs" : "128"
      },
      "read" : {
        "io_bytes" : 0,
        "io_kbytes" : 0,
        "bw_bytes" : 0,
        "bw" : 0,
        "iops" : 0.000000,
        "runtime" : 0,
        "total_ios" : 0,
        "short_ios" : 0,
        "drop_ios" : 0,
        "slat_ns" : {
          "min" : 0,
          "max" : 0,
          "mean" : 0.000000,
          "stddev" : 0.000000,
          "N" : 0
        },
        "clat_ns" : {
          "min" : 0,
          "max" : 0,
          "mean" : 0.000000,
          "stddev" : 0.000000,
          "N" : 0
        },
        "lat_ns" : {
          "min" : 0,
          "max" : 0,
          "mean" : 0.000000,
          "stddev" : 0.000000,
          "N" : 0
        },
        "bw_min" : 0,
        "bw_max" : 0,
        "bw_agg" : 0.000000,
        "bw_mean" : 0.000000,
        "bw_dev" : 0.000000,
        "bw_samples" : 0,
        "iops_min" : 0,
        "iops_max" : 0,
        "iops_mean" : 0.000000,
        "iops_stddev" : 0.000000,
        "iops_samples" : 0
      },
      "write" : {
        "io_bytes" : 69340233728,
        "io_kbytes" : 67715072,
        "bw_bytes" : 1340581426,
        "bw" : 1309161,
        "iops" : 159.809759,
        "runtime" : 51724,
        "total_ios" : 8266,
        "short_ios" : 0,
        "drop_ios" : 0,
        "slat_ns" : {
          "min" : 273624,
          "max" : 118881551,
          "mean" : 2573518.760948,
          "stddev" : 7744750.880979,
          "N" : 8266
        },
        "clat_ns" : {
          "min" : 37338879,
          "max" : 7525961580,
          "mean" : 780078220.329301,
          "stddev" : 850062286.852410,
          "N" : 8266,
          "percentile" : {
            "1.000000" : 77070336,
            "5.000000" : 139460608,
            "10.000000" : 185597952,
            "20.000000" : 265289728,
            "30.000000" : 337641472,
            "40.000000" : 396361728,
            "50.000000" : 471859200,
            "60.000000" : 566231040,
            "70.000000" : 734003200,
            "80.000000" : 1098907648,
            "90.000000" : 1803550720,
            "95.000000" : 2600468480,
            "99.000000" : 4462739456,
            "99.500000" : 4932501504,
            "99.900000" : 6140461056,
            "99.950000" : 6677331968,
            "99.990000" : 7549747200
          }
        },
        "lat_ns" : {
          "min" : 37914821,
          "max" : 7526486046,
          "mean" : 782651739.090249,
          "stddev" : 850392473.381565,
          "N" : 8266
        },
        "bw_min" : 2093398,
        "bw_max" : 5817004,
        "bw_agg" : 100.000000,
        "bw_mean" : 2667590.701336,
        "bw_dev" : 8199.677819,
        "bw_samples" : 6406,
        "iops_min" : 158,
        "iops_max" : 710,
        "iops_mean" : 320.985746,
        "iops_stddev" : 1.019527,
        "iops_samples" : 6406
      },
      "trim" : {
        "io_bytes" : 0,
        "io_kbytes" : 0,
        "bw_bytes" : 0,
        "bw" : 0,
        "iops" : 0.000000,
        "runtime" : 0,
        "total_ios" : 0,
        "short_ios" : 0,
        "drop_ios" : 0,
        "slat_ns" : {
          "min" : 0,
          "max" : 0,
          "mean" : 0.000000,
          "stddev" : 0.000000,
          "N" : 0
        },
        "clat_ns" : {
          "min" : 0,
          "max" : 0,
          "mean" : 0.000000,
          "stddev" : 0.000000,
          "N" : 0
        },
        "lat_ns" : {
          "min" : 0,
          "max" : 0,
          "mean" : 0.000000,
          "stddev" : 0.000000,
          "N" : 0
        },
        "bw_min" : 0,
        "bw_max" : 0,
        "bw_agg" : 0.000000,
        "bw_mean" : 0.000000,
        "bw_dev" : 0.000000,
        "bw_samples" : 0,
        "iops_min" : 0,
        "iops_max" : 0,
        "iops_mean" : 0.000000,
        "iops_stddev" : 0.000000,
        "iops_samples" : 0
      },
      "sync" : {
        "total_ios" : 0,
        "lat_ns" : {
          "min" : 0,
          "max" : 0,
          "mean" : 0.000000,
          "stddev" : 0.000000,
          "N" : 0
        }
      },
      "job_runtime" : 6469542,
      "usr_cpu" : 0.034346,
      "sys_cpu" : 0.110966,
      "ctx" : 10588,
      "majf" : 43,
      "minf" : 3388,
      "iodepth_level" : {
        "1" : 100.000000,
        "2" : 0.000000,
        "4" : 0.000000,
        "8" : 0.000000,
        "16" : 0.000000,
        "32" : 0.000000,
        ">=64" : 0.000000
      },
      "iodepth_submit" : {
        "0" : 0.000000,
        "4" : 100.000000,
        "8" : 0.000000,
        "16" : 0.000000,
        "32" : 0.000000,
        "64" : 0.000000,
        ">=64" : 0.000000
      },
      "iodepth_complete" : {
        "0" : 0.000000,
        "4" : 100.000000,
        "8" : 0.000000,
        "16" : 0.000000,
        "32" : 0.000000,
        "64" : 0.000000,
        ">=64" : 0.000000
      },
      "latency_ns" : {
        "2" : 0.000000,
        "4" : 0.000000,
        "10" : 0.000000,
        "20" : 0.000000,
        "50" : 0.000000,
        "100" : 0.000000,
        "250" : 0.000000,
        "500" : 0.000000,
        "750" : 0.000000,
        "1000" : 0.000000
      },
      "latency_us" : {
        "2" : 0.000000,
        "4" : 0.000000,
        "10" : 0.000000,
        "20" : 0.000000,
        "50" : 0.000000,
        "100" : 0.000000,
        "250" : 0.000000,
        "500" : 0.000000,
        "750" : 0.000000,
        "1000" : 0.000000
      },
      "latency_ms" : {
        "2" : 0.000000,
        "4" : 0.000000,
        "10" : 0.000000,
        "20" : 0.000000,
        "50" : 0.120977,
        "100" : 2.056617,
        "250" : 15.860150,
        "500" : 35.410114,
        "750" : 17.021534,
        "1000" : 7.282845,
        "2000" : 14.105976,
        ">=2000" : 8.141786
      },
      "latency_depth" : 1,
      "latency_target" : 0,
      "latency_percentile" : 100.000000,
      "latency_window" : 0,
      "hostname" : "10.128.2.176",
      "port" : 8765
    },
    {
      "jobname" : "Write",
      "groupid" : 0,
      "job_start" : 1733246658436,
      "error" : 0,
      "job options" : {
        "rw" : "write",
        "bs" : "8m",
        "numjobs" : "128"
      },
      "read" : {
        "io_bytes" : 0,
        "io_kbytes" : 0,
        "bw_bytes" : 0,
        "bw" : 0,
        "iops" : 0.000000,
        "runtime" : 0,
        "total_ios" : 0,
        "short_ios" : 0,
        "drop_ios" : 0,
        "slat_ns" : {
          "min" : 0,
          "max" : 0,
          "mean" : 0.000000,
          "stddev" : 0.000000,
          "N" : 0
        },
        "clat_ns" : {
          "min" : 0,
          "max" : 0,
          "mean" : 0.000000,
          "stddev" : 0.000000,
          "N" : 0
        },
        "lat_ns" : {
          "min" : 0,
          "max" : 0,
          "mean" : 0.000000,
          "stddev" : 0.000000,
          "N" : 0
        },
        "bw_min" : 0,
        "bw_max" : 0,
        "bw_agg" : 0.000000,
        "bw_mean" : 0.000000,
        "bw_dev" : 0.000000,
        "bw_samples" : 0,
        "iops_min" : 0,
        "iops_max" : 0,
        "iops_mean" : 0.000000,
        "iops_stddev" : 0.000000,
        "iops_samples" : 0
      },
      "write" : {
        "io_bytes" : 70137151488,
        "io_kbytes" : 68493312,
        "bw_bytes" : 1356565538,
        "bw" : 1324771,
        "iops" : 161.715214,
        "runtime" : 51702,
        "total_ios" : 8361,
        "short_ios" : 0,
        "drop_ios" : 0,
        "slat_ns" : {
          "min" : 222026,
          "max" : 78661132,
          "mean" : 2159810.428059,
          "stddev" : 5661266.826893,
          "N" : 8361
        },
        "clat_ns" : {
          "min" : 36652245,
          "max" : 7592184512,
          "mean" : 771154498.736993,
          "stddev" : 869394230.132679,
          "N" : 8361,
          "percentile" : {
            "1.000000" : 83361792,
            "5.000000" : 139460608,
            "10.000000" : 187695104,
            "20.000000" : 256901120,
            "30.000000" : 320864256,
            "40.000000" : 383778816,
            "50.000000" : 459276288,
            "60.000000" : 566231040,
            "70.000000" : 725614592,
            "80.000000" : 1061158912,
            "90.000000" : 1753219072,
            "95.000000" : 2466250752,
            "99.000000" : 4596957184,
            "99.500000" : 5402263552,
            "99.900000" : 6744440832,
            "99.950000" : 7012876288,
            "99.990000" : 7616856064
          }
        },
        "lat_ns" : {
          "min" : 38477691,
          "max" : 7592793325,
          "mean" : 773314309.165052,
          "stddev" : 869485413.330938,
          "N" : 8361
        },
        "bw_min" : 2078317,
        "bw_max" : 5865599,
        "bw_agg" : 100.000000,
        "bw_mean" : 2682159.279230,
        "bw_dev" : 8248.060475,
        "bw_samples" : 6433,
        "iops_min" : 139,
        "iops_max" : 713,
        "iops_mean" : 318.366084,
        "iops_stddev" : 1.037207,
        "iops_samples" : 6433
      },
      "trim" : {
        "io_bytes" : 0,
        "io_kbytes" : 0,
        "bw_bytes" : 0,
        "bw" : 0,
        "iops" : 0.000000,
        "runtime" : 0,
        "total_ios" : 0,
        "short_ios" : 0,
        "drop_ios" : 0,
        "slat_ns" : {
          "min" : 0,
          "max" : 0,
          "mean" : 0.000000,
          "stddev" : 0.000000,
          "N" : 0
        },
        "clat_ns" : {
          "min" : 0,
          "max" : 0,
          "mean" : 0.000000,
          "stddev" : 0.000000,
          "N" : 0
        },
        "lat_ns" : {
          "min" : 0,
          "max" : 0,
          "mean" : 0.000000,
          "stddev" : 0.000000,
          "N" : 0
        },
        "bw_min" : 0,
        "bw_max" : 0,
        "bw_agg" : 0.000000,
        "bw_mean" : 0.000000,
        "bw_dev" : 0.000000,
        "bw_samples" : 0,
        "iops_min" : 0,
        "iops_max" : 0,
        "iops_mean" : 0.000000,
        "iops_stddev" : 0.000000,
        "iops_samples" : 0
      },
      "sync" : {
        "total_ios" : 0,
        "lat_ns" : {
          "min" : 0,
          "max" : 0,
          "mean" : 0.000000,
          "stddev" : 0.000000,
          "N" : 0
        }
      },
      "job_runtime" : 6465745,
      "usr_cpu" : 0.031860,
      "sys_cpu" : 0.108665,
      "ctx" : 10493,
      "majf" : 24,
      "minf" : 3526,
      "iodepth_level" : {
        "1" : 100.000000,
        "2" : 0.000000,
        "4" : 0.000000,
        "8" : 0.000000,
        "16" : 0.000000,
        "32" : 0.000000,
        ">=64" : 0.000000
      },
      "iodepth_submit" : {
        "0" : 0.000000,
        "4" : 100.000000,
        "8" : 0.000000,
        "16" : 0.000000,
        "32" : 0.000000,
        "64" : 0.000000,
        ">=64" : 0.000000
      },
      "iodepth_complete" : {
        "0" : 0.000000,
        "4" : 100.000000,
        "8" : 0.000000,
        "16" : 0.000000,
        "32" : 0.000000,
        "64" : 0.000000,
        ">=64" : 0.000000
      },
      "latency_ns" : {
        "2" : 0.000000,
        "4" : 0.000000,
        "10" : 0.000000,
        "20" : 0.000000,
        "50" : 0.000000,
        "100" : 0.000000,
        "250" : 0.000000,
        "500" : 0.000000,
        "750" : 0.000000,
        "1000" : 0.000000
      },
      "latency_us" : {
        "2" : 0.000000,
        "4" : 0.000000,
        "10" : 0.000000,
        "20" : 0.000000,
        "50" : 0.000000,
        "100" : 0.000000,
        "250" : 0.000000,
        "500" : 0.000000,
        "750" : 0.000000,
        "1000" : 0.000000
      },
      "latency_ms" : {
        "2" : 0.000000,
        "4" : 0.000000,
        "10" : 0.000000,
        "20" : 0.000000,
        "50" : 0.083722,
        "100" : 1.734242,
        "250" : 17.210860,
        "500" : 35.139337,
        "750" : 16.696567,
        "1000" : 7.487143,
        "2000" : 13.921780,
        ">=2000" : 7.726349
      },
      "latency_depth" : 1,
      "latency_target" : 0,
      "latency_percentile" : 100.000000,
      "latency_window" : 0,
      "hostname" : "10.128.2.178",
      "port" : 8765
    },
    {
      "jobname" : "All clients",
      "groupid" : 0,
      "job_start" : 0,
      "error" : 0,
      "read" : {
        "io_bytes" : 0,
        "io_kbytes" : 0,
        "bw_bytes" : 0,
        "bw" : 0,
        "iops" : 0.000000,
        "runtime" : 0,
        "total_ios" : 0,
        "short_ios" : 0,
        "drop_ios" : 0,
        "slat_ns" : {
          "min" : 0,
          "max" : 0,
          "mean" : 0.000000,
          "stddev" : 0.000000,
          "N" : 0
        },
        "clat_ns" : {
          "min" : 0,
          "max" : 0,
          "mean" : 0.000000,
          "stddev" : 0.000000,
          "N" : 0
        },
        "lat_ns" : {
          "min" : 0,
          "max" : 0,
          "mean" : 0.000000,
          "stddev" : 0.000000,
          "N" : 0
        },
        "bw_min" : 0,
        "bw_max" : 0,
        "bw_agg" : 0.000000,
        "bw_mean" : 0.000000,
        "bw_dev" : 0.000000,
        "bw_samples" : 0,
        "iops_min" : 0,
        "iops_max" : 0,
        "iops_mean" : 0.000000,
        "iops_stddev" : 0.000000,
        "iops_samples" : 0
      },
      "write" : {
        "io_bytes" : 209379655680,
        "io_kbytes" : 204472320,
        "bw_bytes" : 4048017471,
        "bw" : 3953142,
        "iops" : 482.561287,
        "runtime" : 51724,
        "total_ios" : 24960,
        "short_ios" : 0,
        "drop_ios" : 0,
        "slat_ns" : {
          "min" : 222026,
          "max" : 118881551,
          "mean" : 2443202.501402,
          "stddev" : 7141560.205532,
          "N" : 24960
        },
        "clat_ns" : {
          "min" : 27919358,
          "max" : 8160309899,
          "mean" : 774998499.970272,
          "stddev" : 856941832.487192,
          "N" : 24960
        },
        "lat_ns" : {
          "min" : 37504949,
          "max" : 8160842536,
          "mean" : 777441702.471675,
          "stddev" : 857110516.293494,
          "N" : 24960
        },
        "bw_min" : 6256757,
        "bw_max" : 17466480,
        "bw_agg" : 100.000000,
        "bw_mean" : 8007635.701698,
        "bw_dev" : 8184.070494,
        "bw_samples" : 19315,
        "iops_min" : 459,
        "iops_max" : 2128,
        "iops_mean" : 959.687388,
        "iops_stddev" : 1.021277,
        "iops_samples" : 19315
      },
      "trim" : {
        "io_bytes" : 0,
        "io_kbytes" : 0,
        "bw_bytes" : 0,
        "bw" : 0,
        "iops" : 0.000000,
        "runtime" : 0,
        "total_ios" : 0,
        "short_ios" : 0,
        "drop_ios" : 0,
        "slat_ns" : {
          "min" : 0,
          "max" : 0,
          "mean" : 0.000000,
          "stddev" : 0.000000,
          "N" : 0
        },
        "clat_ns" : {
          "min" : 0,
          "max" : 0,
          "mean" : 0.000000,
          "stddev" : 0.000000,
          "N" : 0
        },
        "lat_ns" : {
          "min" : 0,
          "max" : 0,
          "mean" : 0.000000,
          "stddev" : 0.000000,
          "N" : 0
        },
        "bw_min" : 0,
        "bw_max" : 0,
        "bw_agg" : 0.000000,
        "bw_mean" : 0.000000,
        "bw_dev" : 0.000000,
        "bw_samples" : 0,
        "iops_min" : 0,
        "iops_max" : 0,
        "iops_mean" : 0.000000,
        "iops_stddev" : 0.000000,
        "iops_samples" : 0
      },
      "sync" : {
        "total_ios" : 0,
        "lat_ns" : {
          "min" : 0,
          "max" : 0,
          "mean" : 0.000000,
          "stddev" : 0.000000,
          "N" : 0
        }
      },
      "job_runtime" : 19405203,
      "usr_cpu" : 0.033084,
      "sys_cpu" : 0.111434,
      "ctx" : 31461,
      "majf" : 95,
      "minf" : 10318,
      "iodepth_level" : {
        "1" : 100.000000,
        "2" : 0.000000,
        "4" : 0.000000,
        "8" : 0.000000,
        "16" : 0.000000,
        "32" : 0.000000,
        ">=64" : 0.000000
      },
      "iodepth_submit" : {
        "0" : 0.000000,
        "4" : 100.000000,
        "8" : 0.000000,
        "16" : 0.000000,
        "32" : 0.000000,
        "64" : 0.000000,
        ">=64" : 0.000000
      },
      "iodepth_complete" : {
        "0" : 0.000000,
        "4" : 100.000000,
        "8" : 0.000000,
        "16" : 0.000000,
        "32" : 0.000000,
        "64" : 0.000000,
        ">=64" : 0.000000
      },
      "latency_ns" : {
        "2" : 0.000000,
        "4" : 0.000000,
        "10" : 0.000000,
        "20" : 0.000000,
        "50" : 0.000000,
        "100" : 0.000000,
        "250" : 0.000000,
        "500" : 0.000000,
        "750" : 0.000000,
        "1000" : 0.000000
      },
      "latency_us" : {
        "2" : 0.000000,
        "4" : 0.000000,
        "10" : 0.000000,
        "20" : 0.000000,
        "50" : 0.000000,
        "100" : 0.000000,
        "250" : 0.000000,
        "500" : 0.000000,
        "750" : 0.000000,
        "1000" : 0.000000
      },
      "latency_ms" : {
        "2" : 0.000000,
        "4" : 0.000000,
        "10" : 0.000000,
        "20" : 0.000000,
        "50" : 0.116186,
        "100" : 1.891026,
        "250" : 16.350160,
        "500" : 35.376603,
        "750" : 16.714744,
        "1000" : 7.540064,
        "2000" : 14.142628,
        ">=2000" : 7.868590
      },
      "hostname" : "10.128.2.178",
      "port" : 8765
    }
  ],
  "disk_util" : [

  ]
}
