
{
  "fio version" : "fio-3.37",
  "timestamp" : 1732973087,
  "time" : "Sat Nov 30 14:24:47 2024",
  "global options" : {
    "directory" : "/mnt/benchmark/replica1/",
    "ioengine" : "libaio",
    "direct" : "1",
    "buffered" : "0",
    "invalidate" : "1",
    "time_based" : "1",
    "runtime" : "150",
    "size" : "16G",
    "group_reporting" : "1",
    "loops" : "1",
    "directory" : "/mnt/benchmark/replica1/",
    "ioengine" : "libaio",
    "direct" : "1",
    "buffered" : "0",
    "invalidate" : "1",
    "time_based" : "1",
    "runtime" : "150",
    "size" : "16G",
    "group_reporting" : "1",
    "loops" : "1",
    "directory" : "/mnt/benchmark/replica1/",
    "ioengine" : "libaio",
    "direct" : "1",
    "buffered" : "0",
    "invalidate" : "1",
    "time_based" : "1",
    "runtime" : "150",
    "size" : "16G",
    "group_reporting" : "1",
    "loops" : "1",
    "directory" : "/mnt/benchmark/replica1/",
    "ioengine" : "libaio",
    "direct" : "1",
    "buffered" : "0",
    "invalidate" : "1",
    "time_based" : "1",
    "runtime" : "150",
    "size" : "16G",
    "group_reporting" : "1",
    "loops" : "1",
    "directory" : "/mnt/benchmark/replica1/",
    "ioengine" : "libaio",
    "direct" : "1",
    "buffered" : "0",
    "invalidate" : "1",
    "time_based" : "1",
    "runtime" : "150",
    "size" : "16G",
    "group_reporting" : "1",
    "loops" : "1"
  },
  "client_stats" : [
    {
      "jobname" : "Write",
      "groupid" : 0,
      "job_start" : 1732973088881,
      "error" : 0,
      "job options" : {
        "rw" : "write",
        "bs" : "8m",
        "numjobs" : "128"
      },
      "read" : {
        "io_bytes" : 0,
        "io_kbytes" : 0,
        "bw_bytes" : 0,
        "bw" : 0,
        "iops" : 0.000000,
        "runtime" : 0,
        "total_ios" : 0,
        "short_ios" : 0,
        "drop_ios" : 0,
        "slat_ns" : {
          "min" : 0,
          "max" : 0,
          "mean" : 0.000000,
          "stddev" : 0.000000,
          "N" : 0
        },
        "clat_ns" : {
          "min" : 0,
          "max" : 0,
          "mean" : 0.000000,
          "stddev" : 0.000000,
          "N" : 0
        },
        "lat_ns" : {
          "min" : 0,
          "max" : 0,
          "mean" : 0.000000,
          "stddev" : 0.000000,
          "N" : 0
        },
        "bw_min" : 0,
        "bw_max" : 0,
        "bw_agg" : 0.000000,
        "bw_mean" : 0.000000,
        "bw_dev" : 0.000000,
        "bw_samples" : 0,
        "iops_min" : 0,
        "iops_max" : 0,
        "iops_mean" : 0.000000,
        "iops_stddev" : 0.000000,
        "iops_samples" : 0
      },
      "write" : {
        "io_bytes" : 137044688896,
        "io_kbytes" : 133832704,
        "bw_bytes" : 883623408,
        "bw" : 862913,
        "iops" : 105.336119,
        "runtime" : 155094,
        "total_ios" : 16337,
        "short_ios" : 0,
        "drop_ios" : 0,
        "slat_ns" : {
          "min" : 290123,
          "max" : 100963718,
          "mean" : 1946605.467650,
          "stddev" : 6032825.560593,
          "N" : 16337
        },
        "clat_ns" : {
          "min" : 22538637,
          "max" : 16353078103,
          "mean" : 1183890577.427801,
          "stddev" : 1617553178.789103,
          "N" : 16337,
          "percentile" : {
            "1.000000" : 40632320,
            "5.000000" : 86507520,
            "10.000000" : 141557760,
            "20.000000" : 227540992,
            "30.000000" : 325058560,
            "40.000000" : 442499072,
            "50.000000" : 583008256,
            "60.000000" : 775946240,
            "70.000000" : 1098907648,
            "80.000000" : 1719664640,
            "90.000000" : 3103784960,
            "95.000000" : 4328521728,
            "99.000000" : 8422162432,
            "99.500000" : 9730785280,
            "99.900000" : 14294188032,
            "99.950000" : 15367929856,
            "99.990000" : 15770583040
          }
        },
        "lat_ns" : {
          "min" : 30243198,
          "max" : 16353740493,
          "mean" : 1185837182.895452,
          "stddev" : 1617576856.388277,
          "N" : 16337
        },
        "bw_min" : 2095865,
        "bw_max" : 6684737,
        "bw_agg" : 100.000000,
        "bw_mean" : 2675071.621508,
        "bw_dev" : 8615.823398,
        "bw_samples" : 12713,
        "iops_min" : 217,
        "iops_max" : 816,
        "iops_mean" : 326.029891,
        "iops_stddev" : 1.054356,
        "iops_samples" : 12713
      },
      "trim" : {
        "io_bytes" : 0,
        "io_kbytes" : 0,
        "bw_bytes" : 0,
        "bw" : 0,
        "iops" : 0.000000,
        "runtime" : 0,
        "total_ios" : 0,
        "short_ios" : 0,
        "drop_ios" : 0,
        "slat_ns" : {
          "min" : 0,
          "max" : 0,
          "mean" : 0.000000,
          "stddev" : 0.000000,
          "N" : 0
        },
        "clat_ns" : {
          "min" : 0,
          "max" : 0,
          "mean" : 0.000000,
          "stddev" : 0.000000,
          "N" : 0
        },
        "lat_ns" : {
          "min" : 0,
          "max" : 0,
          "mean" : 0.000000,
          "stddev" : 0.000000,
          "N" : 0
        },
        "bw_min" : 0,
        "bw_max" : 0,
        "bw_agg" : 0.000000,
        "bw_mean" : 0.000000,
        "bw_dev" : 0.000000,
        "bw_samples" : 0,
        "iops_min" : 0,
        "iops_max" : 0,
        "iops_mean" : 0.000000,
        "iops_stddev" : 0.000000,
        "iops_samples" : 0
      },
      "sync" : {
        "total_ios" : 0,
        "lat_ns" : {
          "min" : 0,
          "max" : 0,
          "mean" : 0.000000,
          "stddev" : 0.000000,
          "N" : 0
        }
      },
      "job_runtime" : 19373348,
      "usr_cpu" : 0.023016,
      "sys_cpu" : 0.065709,
      "ctx" : 19505,
      "majf" : 63,
      "minf" : 3533,
      "iodepth_level" : {
        "1" : 100.000000,
        "2" : 0.000000,
        "4" : 0.000000,
        "8" : 0.000000,
        "16" : 0.000000,
        "32" : 0.000000,
        ">=64" : 0.000000
      },
      "iodepth_submit" : {
        "0" : 0.000000,
        "4" : 100.000000,
        "8" : 0.000000,
        "16" : 0.000000,
        "32" : 0.000000,
        "64" : 0.000000,
        ">=64" : 0.000000
      },
      "iodepth_complete" : {
        "0" : 0.000000,
        "4" : 100.000000,
        "8" : 0.000000,
        "16" : 0.000000,
        "32" : 0.000000,
        "64" : 0.000000,
        ">=64" : 0.000000
      },
      "latency_ns" : {
        "2" : 0.000000,
        "4" : 0.000000,
        "10" : 0.000000,
        "20" : 0.000000,
        "50" : 0.000000,
        "100" : 0.000000,
        "250" : 0.000000,
        "500" : 0.000000,
        "750" : 0.000000,
        "1000" : 0.000000
      },
      "latency_us" : {
        "2" : 0.000000,
        "4" : 0.000000,
        "10" : 0.000000,
        "20" : 0.000000,
        "50" : 0.000000,
        "100" : 0.000000,
        "250" : 0.000000,
        "500" : 0.000000,
        "750" : 0.000000,
        "1000" : 0.000000
      },
      "latency_ms" : {
        "2" : 0.000000,
        "4" : 0.000000,
        "10" : 0.000000,
        "20" : 0.000000,
        "50" : 2.142376,
        "100" : 4.009304,
        "250" : 16.024974,
        "500" : 21.876722,
        "750" : 14.678338,
        "1000" : 8.900043,
        "2000" : 14.990512,
        ">=2000" : 17.377732
      },
      "latency_depth" : 1,
      "latency_target" : 0,
      "latency_percentile" : 100.000000,
      "latency_window" : 0,
      "hostname" : "10.128.2.177",
      "port" : 8765
    },
    {
      "jobname" : "Write",
      "groupid" : 0,
      "job_start" : 1732973088857,
      "error" : 0,
      "job options" : {
        "rw" : "write",
        "bs" : "8m",
        "numjobs" : "128"
      },
      "read" : {
        "io_bytes" : 0,
        "io_kbytes" : 0,
        "bw_bytes" : 0,
        "bw" : 0,
        "iops" : 0.000000,
        "runtime" : 0,
        "total_ios" : 0,
        "short_ios" : 0,
        "drop_ios" : 0,
        "slat_ns" : {
          "min" : 0,
          "max" : 0,
          "mean" : 0.000000,
          "stddev" : 0.000000,
          "N" : 0
        },
        "clat_ns" : {
          "min" : 0,
          "max" : 0,
          "mean" : 0.000000,
          "stddev" : 0.000000,
          "N" : 0
        },
        "lat_ns" : {
          "min" : 0,
          "max" : 0,
          "mean" : 0.000000,
          "stddev" : 0.000000,
          "N" : 0
        },
        "bw_min" : 0,
        "bw_max" : 0,
        "bw_agg" : 0.000000,
        "bw_mean" : 0.000000,
        "bw_dev" : 0.000000,
        "bw_samples" : 0,
        "iops_min" : 0,
        "iops_max" : 0,
        "iops_mean" : 0.000000,
        "iops_stddev" : 0.000000,
        "iops_samples" : 0
      },
      "write" : {
        "io_bytes" : 139921981440,
        "io_kbytes" : 136642560,
        "bw_bytes" : 901594014,
        "bw" : 880462,
        "iops" : 107.478382,
        "runtime" : 155194,
        "total_ios" : 16680,
        "short_ios" : 0,
        "drop_ios" : 0,
        "slat_ns" : {
          "min" : 144181,
          "max" : 36272765,
          "mean" : 790303.781355,
          "stddev" : 1656222.805753,
          "N" : 16680
        },
        "clat_ns" : {
          "min" : 18333533,
          "max" : 16023391504,
          "mean" : 1159683427.379976,
          "stddev" : 1614782092.732324,
          "N" : 16680,
          "percentile" : {
            "1.000000" : 28704768,
            "5.000000" : 73924608,
            "10.000000" : 128450560,
            "20.000000" : 217055232,
            "30.000000" : 316669952,
            "40.000000" : 429916160,
            "50.000000" : 574619648,
            "60.000000" : 767557632,
            "70.000000" : 1069547520,
            "80.000000" : 1669332992,
            "90.000000" : 3036676096,
            "95.000000" : 4244635648,
            "99.000000" : 8287944704,
            "99.500000" : 9865003008,
            "99.900000" : 14965276672,
            "99.950000" : 15367929856,
            "99.990000" : 15770583040
          }
        },
        "lat_ns" : {
          "min" : 19361295,
          "max" : 16023789642,
          "mean" : 1160473731.161331,
          "stddev" : 1614751039.336141,
          "N" : 16680
        },
        "bw_min" : 2090914,
        "bw_max" : 6963399,
        "bw_agg" : 100.000000,
        "bw_mean" : 2706106.665550,
        "bw_dev" : 8942.226252,
        "bw_samples" : 12832,
        "iops_min" : 253,
        "iops_max" : 849,
        "iops_mean" : 330.262140,
        "iops_stddev" : 1.091213,
        "iops_samples" : 12832
      },
      "trim" : {
        "io_bytes" : 0,
        "io_kbytes" : 0,
        "bw_bytes" : 0,
        "bw" : 0,
        "iops" : 0.000000,
        "runtime" : 0,
        "total_ios" : 0,
        "short_ios" : 0,
        "drop_ios" : 0,
        "slat_ns" : {
          "min" : 0,
          "max" : 0,
          "mean" : 0.000000,
          "stddev" : 0.000000,
          "N" : 0
        },
        "clat_ns" : {
          "min" : 0,
          "max" : 0,
          "mean" : 0.000000,
          "stddev" : 0.000000,
          "N" : 0
        },
        "lat_ns" : {
          "min" : 0,
          "max" : 0,
          "mean" : 0.000000,
          "stddev" : 0.000000,
          "N" : 0
        },
        "bw_min" : 0,
        "bw_max" : 0,
        "bw_agg" : 0.000000,
        "bw_mean" : 0.000000,
        "bw_dev" : 0.000000,
        "bw_samples" : 0,
        "iops_min" : 0,
        "iops_max" : 0,
        "iops_mean" : 0.000000,
        "iops_stddev" : 0.000000,
        "iops_samples" : 0
      },
      "sync" : {
        "total_ios" : 0,
        "lat_ns" : {
          "min" : 0,
          "max" : 0,
          "mean" : 0.000000,
          "stddev" : 0.000000,
          "N" : 0
        }
      },
      "job_runtime" : 19356798,
      "usr_cpu" : 0.021589,
      "sys_cpu" : 0.033663,
      "ctx" : 17982,
      "majf" : 33,
      "minf" : 3435,
      "iodepth_level" : {
        "1" : 100.000000,
        "2" : 0.000000,
        "4" : 0.000000,
        "8" : 0.000000,
        "16" : 0.000000,
        "32" : 0.000000,
        ">=64" : 0.000000
      },
      "iodepth_submit" : {
        "0" : 0.000000,
        "4" : 100.000000,
        "8" : 0.000000,
        "16" : 0.000000,
        "32" : 0.000000,
        "64" : 0.000000,
        ">=64" : 0.000000
      },
      "iodepth_complete" : {
        "0" : 0.000000,
        "4" : 100.000000,
        "8" : 0.000000,
        "16" : 0.000000,
        "32" : 0.000000,
        "64" : 0.000000,
        ">=64" : 0.000000
      },
      "latency_ns" : {
        "2" : 0.000000,
        "4" : 0.000000,
        "10" : 0.000000,
        "20" : 0.000000,
        "50" : 0.000000,
        "100" : 0.000000,
        "250" : 0.000000,
        "500" : 0.000000,
        "750" : 0.000000,
        "1000" : 0.000000
      },
      "latency_us" : {
        "2" : 0.000000,
        "4" : 0.000000,
        "10" : 0.000000,
        "20" : 0.000000,
        "50" : 0.000000,
        "100" : 0.000000,
        "250" : 0.000000,
        "500" : 0.000000,
        "750" : 0.000000,
        "1000" : 0.000000
      },
      "latency_ms" : {
        "2" : 0.000000,
        "4" : 0.000000,
        "10" : 0.000000,
        "20" : 0.035971,
        "50" : 3.111511,
        "100" : 3.896882,
        "250" : 16.492806,
        "500" : 21.372902,
        "750" : 14.466427,
        "1000" : 8.723022,
        "2000" : 15.077938,
        ">=2000" : 16.822542
      },
      "latency_depth" : 1,
      "latency_target" : 0,
      "latency_percentile" : 100.000000,
      "latency_window" : 0,
      "hostname" : "10.128.2.175",
      "port" : 8765
    },
    {
      "jobname" : "Write",
      "groupid" : 0,
      "job_start" : 1732973088861,
      "error" : 0,
      "job options" : {
        "rw" : "write",
        "bs" : "8m",
        "numjobs" : "128"
      },
      "read" : {
        "io_bytes" : 0,
        "io_kbytes" : 0,
        "bw_bytes" : 0,
        "bw" : 0,
        "iops" : 0.000000,
        "runtime" : 0,
        "total_ios" : 0,
        "short_ios" : 0,
        "drop_ios" : 0,
        "slat_ns" : {
          "min" : 0,
          "max" : 0,
          "mean" : 0.000000,
          "stddev" : 0.000000,
          "N" : 0
        },
        "clat_ns" : {
          "min" : 0,
          "max" : 0,
          "mean" : 0.000000,
          "stddev" : 0.000000,
          "N" : 0
        },
        "lat_ns" : {
          "min" : 0,
          "max" : 0,
          "mean" : 0.000000,
          "stddev" : 0.000000,
          "N" : 0
        },
        "bw_min" : 0,
        "bw_max" : 0,
        "bw_agg" : 0.000000,
        "bw_mean" : 0.000000,
        "bw_dev" : 0.000000,
        "bw_samples" : 0,
        "iops_min" : 0,
        "iops_max" : 0,
        "iops_mean" : 0.000000,
        "iops_stddev" : 0.000000,
        "iops_samples" : 0
      },
      "write" : {
        "io_bytes" : 139032788992,
        "io_kbytes" : 135774208,
        "bw_bytes" : 895754794,
        "bw" : 874760,
        "iops" : 106.782293,
        "runtime" : 155213,
        "total_ios" : 16574,
        "short_ios" : 0,
        "drop_ios" : 0,
        "slat_ns" : {
          "min" : 189626,
          "max" : 49672871,
          "mean" : 1440694.870761,
          "stddev" : 3323151.567378,
          "N" : 16574
        },
        "clat_ns" : {
          "min" : 29023569,
          "max" : 15808264291,
          "mean" : 1166455616.953603,
          "stddev" : 1629253074.818444,
          "N" : 16574,
          "percentile" : {
            "1.000000" : 40108032,
            "5.000000" : 83361792,
            "10.000000" : 137363456,
            "20.000000" : 225443840,
            "30.000000" : 329252864,
            "40.000000" : 442499072,
            "50.000000" : 583008256,
            "60.000000" : 767557632,
            "70.000000" : 1069547520,
            "80.000000" : 1669332992,
            "90.000000" : 3003121664,
            "95.000000" : 4211081216,
            "99.000000" : 8489271296,
            "99.500000" : 9999220736,
            "99.900000" : 14831058944,
            "99.950000" : 15367929856,
            "99.990000" : 15502147584
          }
        },
        "lat_ns" : {
          "min" : 29505233,
          "max" : 15808719996,
          "mean" : 1167896311.824364,
          "stddev" : 1629268794.765793,
          "N" : 16574
        },
        "bw_min" : 2096756,
        "bw_max" : 6782976,
        "bw_agg" : 100.000000,
        "bw_mean" : 2673922.135054,
        "bw_dev" : 8629.593929,
        "bw_samples" : 12892,
        "iops_min" : 245,
        "iops_max" : 828,
        "iops_mean" : 326.294287,
        "iops_stddev" : 1.054234,
        "iops_samples" : 12892
      },
      "trim" : {
        "io_bytes" : 0,
        "io_kbytes" : 0,
        "bw_bytes" : 0,
        "bw" : 0,
        "iops" : 0.000000,
        "runtime" : 0,
        "total_ios" : 0,
        "short_ios" : 0,
        "drop_ios" : 0,
        "slat_ns" : {
          "min" : 0,
          "max" : 0,
          "mean" : 0.000000,
          "stddev" : 0.000000,
          "N" : 0
        },
        "clat_ns" : {
          "min" : 0,
          "max" : 0,
          "mean" : 0.000000,
          "stddev" : 0.000000,
          "N" : 0
        },
        "lat_ns" : {
          "min" : 0,
          "max" : 0,
          "mean" : 0.000000,
          "stddev" : 0.000000,
          "N" : 0
        },
        "bw_min" : 0,
        "bw_max" : 0,
        "bw_agg" : 0.000000,
        "bw_mean" : 0.000000,
        "bw_dev" : 0.000000,
        "bw_samples" : 0,
        "iops_min" : 0,
        "iops_max" : 0,
        "iops_mean" : 0.000000,
        "iops_stddev" : 0.000000,
        "iops_samples" : 0
      },
      "sync" : {
        "total_ios" : 0,
        "lat_ns" : {
          "min" : 0,
          "max" : 0,
          "mean" : 0.000000,
          "stddev" : 0.000000,
          "N" : 0
        }
      },
      "job_runtime" : 19357610,
      "usr_cpu" : 0.019481,
      "sys_cpu" : 0.058081,
      "ctx" : 19411,
      "majf" : 23,
      "minf" : 3560,
      "iodepth_level" : {
        "1" : 100.000000,
        "2" : 0.000000,
        "4" : 0.000000,
        "8" : 0.000000,
        "16" : 0.000000,
        "32" : 0.000000,
        ">=64" : 0.000000
      },
      "iodepth_submit" : {
        "0" : 0.000000,
        "4" : 100.000000,
        "8" : 0.000000,
        "16" : 0.000000,
        "32" : 0.000000,
        "64" : 0.000000,
        ">=64" : 0.000000
      },
      "iodepth_complete" : {
        "0" : 0.000000,
        "4" : 100.000000,
        "8" : 0.000000,
        "16" : 0.000000,
        "32" : 0.000000,
        "64" : 0.000000,
        ">=64" : 0.000000
      },
      "latency_ns" : {
        "2" : 0.000000,
        "4" : 0.000000,
        "10" : 0.000000,
        "20" : 0.000000,
        "50" : 0.000000,
        "100" : 0.000000,
        "250" : 0.000000,
        "500" : 0.000000,
        "750" : 0.000000,
        "1000" : 0.000000
      },
      "latency_us" : {
        "2" : 0.000000,
        "4" : 0.000000,
        "10" : 0.000000,
        "20" : 0.000000,
        "50" : 0.000000,
        "100" : 0.000000,
        "250" : 0.000000,
        "500" : 0.000000,
        "750" : 0.000000,
        "1000" : 0.000000
      },
      "latency_ms" : {
        "2" : 0.000000,
        "4" : 0.000000,
        "10" : 0.000000,
        "20" : 0.000000,
        "50" : 2.310848,
        "100" : 3.933872,
        "250" : 16.290576,
        "500" : 21.714734,
        "750" : 15.210571,
        "1000" : 8.821045,
        "2000" : 15.011464,
        ">=2000" : 16.706890
      },
      "latency_depth" : 1,
      "latency_target" : 0,
      "latency_percentile" : 100.000000,
      "latency_window" : 0,
      "hostname" : "10.128.2.178",
      "port" : 8765
    },
    {
      "jobname" : "Write",
      "groupid" : 0,
      "job_start" : 1732973088880,
      "error" : 0,
      "job options" : {
        "rw" : "write",
        "bs" : "8m",
        "numjobs" : "128"
      },
      "read" : {
        "io_bytes" : 0,
        "io_kbytes" : 0,
        "bw_bytes" : 0,
        "bw" : 0,
        "iops" : 0.000000,
        "runtime" : 0,
        "total_ios" : 0,
        "short_ios" : 0,
        "drop_ios" : 0,
        "slat_ns" : {
          "min" : 0,
          "max" : 0,
          "mean" : 0.000000,
          "stddev" : 0.000000,
          "N" : 0
        },
        "clat_ns" : {
          "min" : 0,
          "max" : 0,
          "mean" : 0.000000,
          "stddev" : 0.000000,
          "N" : 0
        },
        "lat_ns" : {
          "min" : 0,
          "max" : 0,
          "mean" : 0.000000,
          "stddev" : 0.000000,
          "N" : 0
        },
        "bw_min" : 0,
        "bw_max" : 0,
        "bw_agg" : 0.000000,
        "bw_mean" : 0.000000,
        "bw_dev" : 0.000000,
        "bw_samples" : 0,
        "iops_min" : 0,
        "iops_max" : 0,
        "iops_mean" : 0.000000,
        "iops_stddev" : 0.000000,
        "iops_samples" : 0
      },
      "write" : {
        "io_bytes" : 138898571264,
        "io_kbytes" : 135643136,
        "bw_bytes" : 895068830,
        "bw" : 874090,
        "iops" : 106.700519,
        "runtime" : 155182,
        "total_ios" : 16558,
        "short_ios" : 0,
        "drop_ios" : 0,
        "slat_ns" : {
          "min" : 288722,
          "max" : 92569837,
          "mean" : 1917438.902162,
          "stddev" : 5847001.277915,
          "N" : 16558
        },
        "clat_ns" : {
          "min" : 21922317,
          "max" : 16258723331,
          "mean" : 1167333175.311329,
          "stddev" : 1628644673.235423,
          "N" : 16558,
          "percentile" : {
            "1.000000" : 40632320,
            "5.000000" : 83361792,
            "10.000000" : 135266304,
            "20.000000" : 227540992,
            "30.000000" : 325058560,
            "40.000000" : 438304768,
            "50.000000" : 591396864,
            "60.000000" : 775946240,
            "70.000000" : 1082130432,
            "80.000000" : 1686110208,
            "90.000000" : 3003121664,
            "95.000000" : 4244635648,
            "99.000000" : 8489271296,
            "99.500000" : 9865003008,
            "99.900000" : 14696841216,
            "99.950000" : 15502147584,
            "99.990000" : 16307453952
          }
        },
        "lat_ns" : {
          "min" : 23355326,
          "max" : 16259502402,
          "mean" : 1169250614.213491,
          "stddev" : 1628642699.447174,
          "N" : 16558
        },
        "bw_min" : 2091828,
        "bw_max" : 6701056,
        "bw_agg" : 100.000000,
        "bw_mean" : 2679615.978584,
        "bw_dev" : 8556.017426,
        "bw_samples" : 12857,
        "iops_min" : 140,
        "iops_max" : 818,
        "iops_mean" : 323.362672,
        "iops_stddev" : 1.062302,
        "iops_samples" : 12857
      },
      "trim" : {
        "io_bytes" : 0,
        "io_kbytes" : 0,
        "bw_bytes" : 0,
        "bw" : 0,
        "iops" : 0.000000,
        "runtime" : 0,
        "total_ios" : 0,
        "short_ios" : 0,
        "drop_ios" : 0,
        "slat_ns" : {
          "min" : 0,
          "max" : 0,
          "mean" : 0.000000,
          "stddev" : 0.000000,
          "N" : 0
        },
        "clat_ns" : {
          "min" : 0,
          "max" : 0,
          "mean" : 0.000000,
          "stddev" : 0.000000,
          "N" : 0
        },
        "lat_ns" : {
          "min" : 0,
          "max" : 0,
          "mean" : 0.000000,
          "stddev" : 0.000000,
          "N" : 0
        },
        "bw_min" : 0,
        "bw_max" : 0,
        "bw_agg" : 0.000000,
        "bw_mean" : 0.000000,
        "bw_dev" : 0.000000,
        "bw_samples" : 0,
        "iops_min" : 0,
        "iops_max" : 0,
        "iops_mean" : 0.000000,
        "iops_stddev" : 0.000000,
        "iops_samples" : 0
      },
      "sync" : {
        "total_ios" : 0,
        "lat_ns" : {
          "min" : 0,
          "max" : 0,
          "mean" : 0.000000,
          "stddev" : 0.000000,
          "N" : 0
        }
      },
      "job_runtime" : 19360928,
      "usr_cpu" : 0.025211,
      "sys_cpu" : 0.065395,
      "ctx" : 19459,
      "majf" : 35,
      "minf" : 3549,
      "iodepth_level" : {
        "1" : 100.000000,
        "2" : 0.000000,
        "4" : 0.000000,
        "8" : 0.000000,
        "16" : 0.000000,
        "32" : 0.000000,
        ">=64" : 0.000000
      },
      "iodepth_submit" : {
        "0" : 0.000000,
        "4" : 100.000000,
        "8" : 0.000000,
        "16" : 0.000000,
        "32" : 0.000000,
        "64" : 0.000000,
        ">=64" : 0.000000
      },
      "iodepth_complete" : {
        "0" : 0.000000,
        "4" : 100.000000,
        "8" : 0.000000,
        "16" : 0.000000,
        "32" : 0.000000,
        "64" : 0.000000,
        ">=64" : 0.000000
      },
      "latency_ns" : {
        "2" : 0.000000,
        "4" : 0.000000,
        "10" : 0.000000,
        "20" : 0.000000,
        "50" : 0.000000,
        "100" : 0.000000,
        "250" : 0.000000,
        "500" : 0.000000,
        "750" : 0.000000,
        "1000" : 0.000000
      },
      "latency_us" : {
        "2" : 0.000000,
        "4" : 0.000000,
        "10" : 0.000000,
        "20" : 0.000000,
        "50" : 0.000000,
        "100" : 0.000000,
        "250" : 0.000000,
        "500" : 0.000000,
        "750" : 0.000000,
        "1000" : 0.000000
      },
      "latency_ms" : {
        "2" : 0.000000,
        "4" : 0.000000,
        "10" : 0.000000,
        "20" : 0.000000,
        "50" : 2.041309,
        "100" : 4.306076,
        "250" : 15.949994,
        "500" : 22.122237,
        "750" : 14.403914,
        "1000" : 9.204010,
        "2000" : 15.176954,
        ">=2000" : 16.795507
      },
      "latency_depth" : 1,
      "latency_target" : 0,
      "latency_percentile" : 100.000000,
      "latency_window" : 0,
      "hostname" : "10.128.2.174",
      "port" : 8765
    },
    {
      "jobname" : "Write",
      "groupid" : 0,
      "job_start" : 1732973088891,
      "error" : 0,
      "job options" : {
        "rw" : "write",
        "bs" : "8m",
        "numjobs" : "128"
      },
      "read" : {
        "io_bytes" : 0,
        "io_kbytes" : 0,
        "bw_bytes" : 0,
        "bw" : 0,
        "iops" : 0.000000,
        "runtime" : 0,
        "total_ios" : 0,
        "short_ios" : 0,
        "drop_ios" : 0,
        "slat_ns" : {
          "min" : 0,
          "max" : 0,
          "mean" : 0.000000,
          "stddev" : 0.000000,
          "N" : 0
        },
        "clat_ns" : {
          "min" : 0,
          "max" : 0,
          "mean" : 0.000000,
          "stddev" : 0.000000,
          "N" : 0
        },
        "lat_ns" : {
          "min" : 0,
          "max" : 0,
          "mean" : 0.000000,
          "stddev" : 0.000000,
          "N" : 0
        },
        "bw_min" : 0,
        "bw_max" : 0,
        "bw_agg" : 0.000000,
        "bw_mean" : 0.000000,
        "bw_dev" : 0.000000,
        "bw_samples" : 0,
        "iops_min" : 0,
        "iops_max" : 0,
        "iops_mean" : 0.000000,
        "iops_stddev" : 0.000000,
        "iops_samples" : 0
      },
      "write" : {
        "io_bytes" : 135215972352,
        "io_kbytes" : 132046848,
        "bw_bytes" : 870788075,
        "bw" : 850378,
        "iops" : 103.806028,
        "runtime" : 155280,
        "total_ios" : 16119,
        "short_ios" : 0,
        "drop_ios" : 0,
        "slat_ns" : {
          "min" : 278202,
          "max" : 162044808,
          "mean" : 1958039.289968,
          "stddev" : 6569545.723279,
          "N" : 16119
        },
        "clat_ns" : {
          "min" : 25077044,
          "max" : 15985735867,
          "mean" : 1199603460.291147,
          "stddev" : 1674969953.875689,
          "N" : 16119,
          "percentile" : {
            "1.000000" : 40108032,
            "5.000000" : 84410368,
            "10.000000" : 137363456,
            "20.000000" : 227540992,
            "30.000000" : 320864256,
            "40.000000" : 438304768,
            "50.000000" : 591396864,
            "60.000000" : 792723456,
            "70.000000" : 1115684864,
            "80.000000" : 1753219072,
            "90.000000" : 3103784960,
            "95.000000" : 4328521728,
            "99.000000" : 8556380160,
            "99.500000" : 9999220736,
            "99.900000" : 15233712128,
            "99.950000" : 15636365312,
            "99.990000" : 15904800768
          }
        },
        "lat_ns" : {
          "min" : 26104194,
          "max" : 15986355261,
          "mean" : 1201561499.581115,
          "stddev" : 1675022909.174424,
          "N" : 16119
        },
        "bw_min" : 2093659,
        "bw_max" : 6864896,
        "bw_agg" : 100.000000,
        "bw_mean" : 2675080.487013,
        "bw_dev" : 8701.541496,
        "bw_samples" : 12538,
        "iops_min" : 160,
        "iops_max" : 838,
        "iops_mean" : 324.567083,
        "iops_stddev" : 1.069202,
        "iops_samples" : 12538
      },
      "trim" : {
        "io_bytes" : 0,
        "io_kbytes" : 0,
        "bw_bytes" : 0,
        "bw" : 0,
        "iops" : 0.000000,
        "runtime" : 0,
        "total_ios" : 0,
        "short_ios" : 0,
        "drop_ios" : 0,
        "slat_ns" : {
          "min" : 0,
          "max" : 0,
          "mean" : 0.000000,
          "stddev" : 0.000000,
          "N" : 0
        },
        "clat_ns" : {
          "min" : 0,
          "max" : 0,
          "mean" : 0.000000,
          "stddev" : 0.000000,
          "N" : 0
        },
        "lat_ns" : {
          "min" : 0,
          "max" : 0,
          "mean" : 0.000000,
          "stddev" : 0.000000,
          "N" : 0
        },
        "bw_min" : 0,
        "bw_max" : 0,
        "bw_agg" : 0.000000,
        "bw_mean" : 0.000000,
        "bw_dev" : 0.000000,
        "bw_samples" : 0,
        "iops_min" : 0,
        "iops_max" : 0,
        "iops_mean" : 0.000000,
        "iops_stddev" : 0.000000,
        "iops_samples" : 0
      },
      "sync" : {
        "total_ios" : 0,
        "lat_ns" : {
          "min" : 0,
          "max" : 0,
          "mean" : 0.000000,
          "stddev" : 0.000000,
          "N" : 0
        }
      },
      "job_runtime" : 19368244,
      "usr_cpu" : 0.024468,
      "sys_cpu" : 0.061957,
      "ctx" : 19057,
      "majf" : 38,
      "minf" : 3420,
      "iodepth_level" : {
        "1" : 100.000000,
        "2" : 0.000000,
        "4" : 0.000000,
        "8" : 0.000000,
        "16" : 0.000000,
        "32" : 0.000000,
        ">=64" : 0.000000
      },
      "iodepth_submit" : {
        "0" : 0.000000,
        "4" : 100.000000,
        "8" : 0.000000,
        "16" : 0.000000,
        "32" : 0.000000,
        "64" : 0.000000,
        ">=64" : 0.000000
      },
      "iodepth_complete" : {
        "0" : 0.000000,
        "4" : 100.000000,
        "8" : 0.000000,
        "16" : 0.000000,
        "32" : 0.000000,
        "64" : 0.000000,
        ">=64" : 0.000000
      },
      "latency_ns" : {
        "2" : 0.000000,
        "4" : 0.000000,
        "10" : 0.000000,
        "20" : 0.000000,
        "50" : 0.000000,
        "100" : 0.000000,
        "250" : 0.000000,
        "500" : 0.000000,
        "750" : 0.000000,
        "1000" : 0.000000
      },
      "latency_us" : {
        "2" : 0.000000,
        "4" : 0.000000,
        "10" : 0.000000,
        "20" : 0.000000,
        "50" : 0.000000,
        "100" : 0.000000,
        "250" : 0.000000,
        "500" : 0.000000,
        "750" : 0.000000,
        "1000" : 0.000000
      },
      "latency_ms" : {
        "2" : 0.000000,
        "4" : 0.000000,
        "10" : 0.000000,
        "20" : 0.000000,
        "50" : 2.289224,
        "100" : 4.119362,
        "250" : 16.154848,
        "500" : 21.843787,
        "750" : 13.896644,
        "1000" : 8.586141,
        "2000" : 15.714374,
        ">=2000" : 17.395620
      },
      "latency_depth" : 1,
      "latency_target" : 0,
      "latency_percentile" : 100.000000,
      "latency_window" : 0,
      "hostname" : "10.128.2.176",
      "port" : 8765
    },
    {
      "jobname" : "All clients",
      "groupid" : 0,
      "job_start" : 0,
      "error" : 0,
      "read" : {
        "io_bytes" : 0,
        "io_kbytes" : 0,
        "bw_bytes" : 0,
        "bw" : 0,
        "iops" : 0.000000,
        "runtime" : 0,
        "total_ios" : 0,
        "short_ios" : 0,
        "drop_ios" : 0,
        "slat_ns" : {
          "min" : 0,
          "max" : 0,
          "mean" : 0.000000,
          "stddev" : 0.000000,
          "N" : 0
        },
        "clat_ns" : {
          "min" : 0,
          "max" : 0,
          "mean" : 0.000000,
          "stddev" : 0.000000,
          "N" : 0
        },
        "lat_ns" : {
          "min" : 0,
          "max" : 0,
          "mean" : 0.000000,
          "stddev" : 0.000000,
          "N" : 0
        },
        "bw_min" : 0,
        "bw_max" : 0,
        "bw_agg" : 0.000000,
        "bw_mean" : 0.000000,
        "bw_dev" : 0.000000,
        "bw_samples" : 0,
        "iops_min" : 0,
        "iops_max" : 0,
        "iops_mean" : 0.000000,
        "iops_stddev" : 0.000000,
        "iops_samples" : 0
      },
      "write" : {
        "io_bytes" : 690114002944,
        "io_kbytes" : 673939456,
        "bw_bytes" : 4444319957,
        "bw" : 4340156,
        "iops" : 529.804225,
        "runtime" : 155280,
        "total_ios" : 82268,
        "short_ios" : 0,
        "drop_ios" : 0,
        "slat_ns" : {
          "min" : 144181,
          "max" : 162044808,
          "mean" : 1606610.420127,
          "stddev" : 5054852.806463,
          "N" : 82268
        },
        "clat_ns" : {
          "min" : 18333533,
          "max" : 16353078103,
          "mean" : 1175216198.531178,
          "stddev" : 1632997547.450380,
          "N" : 82268
        },
        "lat_ns" : {
          "min" : 19361295,
          "max" : 16353740493,
          "mean" : 1176822808.951305,
          "stddev" : 1633012286.590771,
          "N" : 82268
        },
        "bw_min" : 10469022,
        "bw_max" : 33997064,
        "bw_agg" : 100.000000,
        "bw_mean" : 13409796.887709,
        "bw_dev" : 8689.789998,
        "bw_samples" : 63832,
        "iops_min" : 1015,
        "iops_max" : 4149,
        "iops_mean" : 1630.516073,
        "iops_stddev" : 1.066312,
        "iops_samples" : 63832
      },
      "trim" : {
        "io_bytes" : 0,
        "io_kbytes" : 0,
        "bw_bytes" : 0,
        "bw" : 0,
        "iops" : 0.000000,
        "runtime" : 0,
        "total_ios" : 0,
        "short_ios" : 0,
        "drop_ios" : 0,
        "slat_ns" : {
          "min" : 0,
          "max" : 0,
          "mean" : 0.000000,
          "stddev" : 0.000000,
          "N" : 0
        },
        "clat_ns" : {
          "min" : 0,
          "max" : 0,
          "mean" : 0.000000,
          "stddev" : 0.000000,
          "N" : 0
        },
        "lat_ns" : {
          "min" : 0,
          "max" : 0,
          "mean" : 0.000000,
          "stddev" : 0.000000,
          "N" : 0
        },
        "bw_min" : 0,
        "bw_max" : 0,
        "bw_agg" : 0.000000,
        "bw_mean" : 0.000000,
        "bw_dev" : 0.000000,
        "bw_samples" : 0,
        "iops_min" : 0,
        "iops_max" : 0,
        "iops_mean" : 0.000000,
        "iops_stddev" : 0.000000,
        "iops_samples" : 0
      },
      "sync" : {
        "total_ios" : 0,
        "lat_ns" : {
          "min" : 0,
          "max" : 0,
          "mean" : 0.000000,
          "stddev" : 0.000000,
          "N" : 0
        }
      },
      "job_runtime" : 96816928,
      "usr_cpu" : 0.022753,
      "sys_cpu" : 0.056963,
      "ctx" : 95414,
      "majf" : 192,
      "minf" : 17497,
      "iodepth_level" : {
        "1" : 100.000000,
        "2" : 0.000000,
        "4" : 0.000000,
        "8" : 0.000000,
        "16" : 0.000000,
        "32" : 0.000000,
        ">=64" : 0.000000
      },
      "iodepth_submit" : {
        "0" : 0.000000,
        "4" : 100.000000,
        "8" : 0.000000,
        "16" : 0.000000,
        "32" : 0.000000,
        "64" : 0.000000,
        ">=64" : 0.000000
      },
      "iodepth_complete" : {
        "0" : 0.000000,
        "4" : 100.000000,
        "8" : 0.000000,
        "16" : 0.000000,
        "32" : 0.000000,
        "64" : 0.000000,
        ">=64" : 0.000000
      },
      "latency_ns" : {
        "2" : 0.000000,
        "4" : 0.000000,
        "10" : 0.000000,
        "20" : 0.000000,
        "50" : 0.000000,
        "100" : 0.000000,
        "250" : 0.000000,
        "500" : 0.000000,
        "750" : 0.000000,
        "1000" : 0.000000
      },
      "latency_us" : {
        "2" : 0.000000,
        "4" : 0.000000,
        "10" : 0.000000,
        "20" : 0.000000,
        "50" : 0.000000,
        "100" : 0.000000,
        "250" : 0.000000,
        "500" : 0.000000,
        "750" : 0.000000,
        "1000" : 0.000000
      },
      "latency_ms" : {
        "2" : 0.000000,
        "4" : 0.000000,
        "10" : 0.000000,
        "20" : 0.010000,
        "50" : 2.381242,
        "100" : 4.052609,
        "250" : 16.183692,
        "500" : 21.784898,
        "750" : 14.534205,
        "1000" : 8.847912,
        "2000" : 15.191812,
        ">=2000" : 17.016337
      },
      "hostname" : "10.128.2.176",
      "port" : 8765
    }
  ],
  "disk_util" : [

  ]
}
